pyPanDEG/__init__.py
pyPanDEG/cds_downloader.py
pyPanDEG/dataset_downloader.py
pyPanDEG/deg_analyzer.py
pyPanDEG/gene_clusterer.py
pyPanDEG/genecount_modifier.py
pyPanDEG/rna_seq_processor.py
pyPanDEG-0.0.1.dist-info/LICENSE.txt
pyPanDEG-0.0.1.dist-info/METADATA
pyPanDEG-0.0.1.dist-info/WHEEL
pyPanDEG-0.0.1.dist-info/entry_points.txt
pyPanDEG-0.0.1.dist-info/top_level.txt
pyPanDEG-0.0.1.dist-info/RECORD
